pysas/.git/COMMIT_EDITMSG
pysas/.git/FETCH_HEAD
pysas/.git/HEAD
pysas/.git/ORIG_HEAD
pysas/.git/config
pysas/.git/description
pysas/.git/hooks/applypatch-msg.sample
pysas/.git/hooks/commit-msg.sample
pysas/.git/hooks/fsmonitor-watchman.sample
pysas/.git/hooks/post-update.sample
pysas/.git/hooks/pre-applypatch.sample
pysas/.git/hooks/pre-commit.sample
pysas/.git/hooks/pre-merge-commit.sample
pysas/.git/hooks/pre-push.sample
pysas/.git/hooks/pre-rebase.sample
pysas/.git/hooks/pre-receive.sample
pysas/.git/hooks/prepare-commit-msg.sample
pysas/.git/hooks/push-to-checkout.sample
pysas/.git/hooks/update.sample
pysas/.git/index
pysas/.git/info/exclude
pysas/.git/logs/HEAD
pysas/.git/logs/refs/heads/dev_track
pysas/.git/logs/refs/heads/loguru
pysas/.git/logs/refs/heads/main
pysas/.git/logs/refs/heads/pysasv2
pysas/.git/logs/refs/remotes/origin/HEAD
pysas/.git/logs/refs/remotes/origin/dev_track
pysas/.git/logs/refs/remotes/origin/main
pysas/.git/logs/refs/remotes/origin/pysasv2
pysas/.git/objects/00/1e9c212ae3d9c20859faaa5ed673b7e5f07f41
pysas/.git/objects/00/5c1f3faf09010446e68cb2a3433cc5ea766813
pysas/.git/objects/00/760fd52e999fa9610d811db6600043b9e2da6d
pysas/.git/objects/00/db70187073299ddcbdd754775dd9d04d4c52cb
pysas/.git/objects/00/fc70e9dfa4521783a739284157f688f92240c3
pysas/.git/objects/01/86804d1e6aa496e99aa576ec2d70ed9abbb3a5
pysas/.git/objects/01/c34435fbcc0055ae22dc24eeacfcdf600871a3
pysas/.git/objects/02/428ad9c015adbb538f7f6cda57fcae6dd02bed
pysas/.git/objects/02/53a4725e0b34be76b4b410b8c227c4f7077de6
pysas/.git/objects/02/64dfe5341de681b56124f1db6a688792ec930a
pysas/.git/objects/02/ac1a3ef1a963bce456063f8c93521e0ade00d4
pysas/.git/objects/03/13ebdd8f5963d21accd690649278f64044e488
pysas/.git/objects/04/30c810980bae0fc851047da5517bea4cc90549
pysas/.git/objects/04/de94aefcda505871fe48ee24be9160e17c73c0
pysas/.git/objects/05/51ce1ac6a73321f3ffeadcefccbc51630a26ea
pysas/.git/objects/05/705b8326e42bd2643f882cf0ae4a5a0f5c7ab7
xmmpysas-2.2.9.dist-info/METADATA
xmmpysas-2.2.9.dist-info/WHEEL
xmmpysas-2.2.9.dist-info/RECORD
