Metadata-Version: 2.3
Name: xmmpysas
Version: 2.2.9
Summary: Python wrapper for XMM-Newton SAS.
License: GPL-3.0-or-later
Keywords: XMM-Newton,x-ray,astronomy
Author: Ryan Tanner
Author-email: ryan.tanner@nasa.gov
Requires-Python: >=3.10,<4.0
Classifier: Intended Audience :: Science/Research
Classifier: Topic :: Scientific/Engineering :: Astronomy
Requires-Dist: astropy (>=6.1,<8.0.0)
Requires-Dist: astroquery (>=0.4.10,<1.0.0)
Requires-Dist: beautifultable (>=1.1,<2.0.0)
Requires-Dist: loguru (>=0.7.3,<1.0.0)
Requires-Dist: matplotlib (>=3.9,<4.0.0)
Requires-Dist: numpy (>=2.1,<3.0.0)
Requires-Dist: pypdf (>=5.1,<6.0.0)
Requires-Dist: regions (>=0.10,<1.0.0)
Requires-Dist: scipy (>=1.14,<2.0.0)
